[
  1,
  [
    "ecpdLyjvZBwrvm+cedCcQy",
    "11cRO60ZNBCK6Zo3KZUV8n",
    "f7le90aN1HvLnhQebAPSXL",
    "556a7w7whNUaPSFs2H6xEE"
  ],
  [
    "node",
    "_parent",
    "_spriteFrame",
    "_textureSetter",
    "_N$target",
    "card",
    "scene",
    "_normalMaterial"
  ],
  [
    [
      "cc.Node",
      [
        "_name",
        "_objFlags",
        "_id",
        "_components",
        "_contentSize",
        "_children",
        "_parent",
        "_trs",
        "_color"
      ],
      0,
      9,
      5,
      2,
      1,
      7,
      5
    ],
    [
      "cc.Widget",
      [
        "_alignFlags",
        "_originalWidth",
        "_originalHeight",
        "_top",
        "alignMode",
        "node"
      ],
      -2,
      1
    ],
    [
      "cc.Sprite",
      [
        "_sizeMode",
        "_isTrimmedMode",
        "node",
        "_materials",
        "_spriteFrame"
      ],
      1,
      1,
      3,
      6
    ],
    [
      "cc.Button",
      [
        "zoomScale",
        "_N$transition",
        "node",
        "_N$target",
        "_normalMaterial"
      ],
      1,
      1,
      1,
      6
    ],
    [
      "cc.Label",
      [
        "_string",
        "_styleFlags",
        "_N$horizontalAlign",
        "_N$verticalAlign",
        "_fontSize",
        "_lineHeight",
        "_enableWrapText",
        "_N$cacheMode",
        "node",
        "_materials"
      ],
      -5,
      1,
      3
    ],
    "cc.SpriteFrame",
    [
      "cc.SceneAsset",
      [
        "_name",
        "asyncLoadAssets"
      ],
      1
    ],
    [
      "cc.Canvas",
      [
        "_fitWidth",
        "_fitHeight",
        "node",
        "_designResolution"
      ],
      1,
      1,
      5
    ],
    [
      "32ac7U3+OdFpJMImIy13br0",
      [
        "node"
      ],
      3,
      1
    ],
    [
      "4eefcThCNNIv7Hni6oMtecW",
      [
        "node",
        "items"
      ],
      3,
      1,
      9
    ],
    [
      "ResPopupItemInfo",
      [
        "title",
        "url"
      ],
      1
    ],
    [
      "cc.Layout",
      [
        "_resize",
        "_N$layoutType",
        "_N$paddingLeft",
        "_N$paddingRight",
        "node",
        "_layoutSize"
      ],
      -1,
      1,
      5
    ],
    [
      "3cf8arMOblOeL4UxCUU8QcT",
      [
        "node",
        "card",
        "flipBtn"
      ],
      3,
      1,
      1,
      1
    ],
    [
      "cc.Scene",
      [
        "_name",
        "_active",
        "_children",
        "_anchorPoint",
        "_trs"
      ],
      1,
      2,
      5,
      7
    ],
    [
      "cc.Camera",
      [
        "_clearFlags",
        "_depth",
        "node"
      ],
      1,
      1
    ]
  ],
  [
    [
      1,
      0,
      5,
      2
    ],
    [
      0,
      0,
      6,
      5,
      3,
      4,
      2
    ],
    [
      0,
      0,
      6,
      3,
      4,
      7,
      2
    ],
    [
      0,
      0,
      5,
      3,
      4,
      7,
      2
    ],
    [
      1,
      0,
      1,
      2,
      5,
      4
    ],
    [
      2,
      0,
      1,
      2,
      3,
      4,
      3
    ],
    [
      10,
      0,
      1,
      3
    ],
    [
      6,
      0,
      1,
      3
    ],
    [
      0,
      0,
      1,
      2,
      5,
      3,
      4,
      7,
      4
    ],
    [
      0,
      0,
      5,
      3,
      4,
      2
    ],
    [
      0,
      0,
      6,
      3,
      8,
      4,
      2
    ],
    [
      0,
      0,
      1,
      6,
      5,
      3,
      4,
      7,
      3
    ],
    [
      0,
      0,
      1,
      6,
      3,
      8,
      4,
      3
    ],
    [
      7,
      0,
      1,
      2,
      3,
      3
    ],
    [
      1,
      0,
      3,
      5,
      3
    ],
    [
      1,
      4,
      0,
      1,
      2,
      5,
      5
    ],
    [
      8,
      0,
      1
    ],
    [
      2,
      0,
      2,
      3,
      4,
      2
    ],
    [
      3,
      2,
      3,
      4,
      1
    ],
    [
      3,
      0,
      1,
      2,
      3
    ],
    [
      9,
      0,
      1,
      1
    ],
    [
      11,
      0,
      1,
      2,
      3,
      4,
      5,
      5
    ],
    [
      12,
      0,
      1,
      2,
      1
    ],
    [
      13,
      0,
      1,
      2,
      3,
      4,
      3
    ],
    [
      14,
      0,
      1,
      2,
      3
    ],
    [
      4,
      0,
      4,
      5,
      6,
      1,
      2,
      3,
      7,
      8,
      9,
      9
    ],
    [
      4,
      0,
      1,
      2,
      3,
      8,
      9,
      5
    ]
  ],
  [
    [
      [
        {
          "name": "cocos",
          "rect": [
            0,
            0,
            195,
            270
          ],
          "offset": [
            0,
            0
          ],
          "originalSize": [
            195,
            270
          ],
          "capInsets": [
            0,
            0,
            0,
            0
          ]
        }
      ],
      [
        5
      ],
      0,
      [
        0
      ],
      [
        3
      ],
      [
        2
      ]
    ],
    [
      [
        [
          7,
          "flip_card",
          null
        ],
        [
          8,
          "Canvas",
          512,
          "a5esZu+45LA5mBpvttspPD",
          [
            -4,
            -5
          ],
          [
            [
              13,
              true,
              false,
              -1,
              [
                5,
                720,
                1280
              ]
            ],
            [
              0,
              45,
              -2
            ],
            [
              16,
              -3
            ]
          ],
          [
            5,
            720,
            1280
          ],
          [
            360,
            640,
            0,
            0,
            0,
            0,
            1,
            1,
            1,
            1
          ]
        ],
        [
          3,
          "flipBtn",
          [
            -9
          ],
          [
            [
              17,
              0,
              -6,
              [
                5
              ],
              6
            ],
            [
              18,
              -8,
              -7,
              7
            ]
          ],
          [
            5,
            200,
            80
          ],
          [
            0,
            -350,
            0,
            0,
            0,
            0,
            1,
            1,
            1,
            0
          ]
        ],
        [
          3,
          "title",
          [
            -14
          ],
          [
            [
              19,
              1.1,
              3,
              -10
            ],
            [
              20,
              -11,
              [
                [
                  6,
                  "[示例] FlipCard.ts",
                  "https://gitee.com/ifaswind/eazax-cases/blob/master/assets/cases/flip_card/scripts/FlipCard.ts"
                ],
                [
                  6,
                  "TweenUtil.ts",
                  "https://gitee.com/ifaswind/eazax-ccc/blob/master/utils/TweenUtil.ts"
                ]
              ]
            ],
            [
              21,
              1,
              1,
              50,
              50,
              -12,
              [
                5,
                367.95,
                80
              ]
            ],
            [
              14,
              1,
              50,
              -13
            ]
          ],
          [
            5,
            367.95,
            80
          ],
          [
            0,
            550,
            0,
            0,
            0,
            0,
            1,
            1,
            1,
            0
          ]
        ],
        [
          1,
          "Main",
          1,
          [
            -16,
            -17,
            -18
          ],
          [
            [
              0,
              45,
              -15
            ]
          ],
          [
            5,
            720,
            1280
          ]
        ],
        [
          9,
          "FlipCard",
          [
            -22,
            2
          ],
          [
            [
              22,
              -20,
              -19,
              2
            ],
            [
              0,
              45,
              -21
            ]
          ],
          [
            5,
            720,
            1280
          ]
        ],
        [
          1,
          "Background",
          4,
          [
            -24
          ],
          [
            [
              4,
              45,
              2,
              2,
              -23
            ]
          ],
          [
            5,
            720,
            1280
          ]
        ],
        [
          10,
          "background",
          6,
          [
            [
              5,
              0,
              false,
              -25,
              [
                0
              ],
              1
            ],
            [
              4,
              45,
              2,
              2,
              -26
            ]
          ],
          [
            4,
            4282399542
          ],
          [
            5,
            720,
            1280
          ]
        ],
        [
          1,
          "Content",
          4,
          [
            5
          ],
          [
            [
              0,
              45,
              -27
            ]
          ],
          [
            5,
            720,
            1280
          ]
        ],
        [
          2,
          "card",
          5,
          [
            [
              5,
              2,
              false,
              -28,
              [
                2
              ],
              3
            ]
          ],
          [
            5,
            195,
            270
          ],
          [
            0,
            50,
            0,
            0,
            0,
            0,
            1,
            2,
            2,
            1
          ]
        ],
        [
          11,
          "main",
          512,
          2,
          [
            -30
          ],
          [
            [
              15,
              0,
              45,
              100,
              40,
              -29
            ]
          ],
          [
            5,
            200,
            80
          ],
          [
            0,
            0,
            0,
            0,
            0,
            0,
            1,
            1,
            1,
            0
          ]
        ],
        [
          1,
          "UI",
          4,
          [
            3
          ],
          [
            [
              0,
              45,
              -31
            ]
          ],
          [
            5,
            720,
            1280
          ]
        ],
        [
          23,
          "New Node",
          false,
          [
            1
          ],
          [
            0,
            0,
            0
          ],
          [
            0,
            0,
            0,
            0,
            0,
            0,
            1,
            1,
            1,
            1
          ]
        ],
        [
          2,
          "Main Camera",
          1,
          [
            [
              24,
              7,
              -1,
              -32
            ]
          ],
          [
            5,
            960,
            640
          ],
          [
            0,
            0,
            539.5264831639423,
            0,
            0,
            0,
            1,
            1,
            1,
            1
          ]
        ],
        [
          12,
          "label",
          512,
          10,
          [
            [
              25,
              "翻牌",
              25,
              30,
              false,
              1,
              1,
              1,
              1,
              -33,
              [
                4
              ]
            ]
          ],
          [
            4,
            4278190080
          ],
          [
            5,
            50,
            37.8
          ]
        ],
        [
          2,
          "label",
          3,
          [
            [
              26,
              "🔸Flip Card🔸",
              5,
              1,
              1,
              -34,
              [
                8
              ]
            ]
          ],
          [
            5,
            267.95,
            50.4
          ],
          [
            0,
            4.618527782440651e-14,
            0,
            0,
            0,
            0,
            1,
            1,
            1,
            1
          ]
        ]
      ],
      0,
      [
        0,
        0,
        1,
        0,
        0,
        1,
        0,
        0,
        1,
        0,
        -1,
        13,
        0,
        -2,
        4,
        0,
        0,
        2,
        0,
        4,
        2,
        0,
        0,
        2,
        0,
        -1,
        10,
        0,
        0,
        3,
        0,
        0,
        3,
        0,
        0,
        3,
        0,
        0,
        3,
        0,
        -1,
        15,
        0,
        0,
        4,
        0,
        -1,
        6,
        0,
        -2,
        8,
        0,
        -3,
        11,
        0,
        5,
        9,
        0,
        0,
        5,
        0,
        0,
        5,
        0,
        -1,
        9,
        0,
        0,
        6,
        0,
        -1,
        7,
        0,
        0,
        7,
        0,
        0,
        7,
        0,
        0,
        8,
        0,
        0,
        9,
        0,
        0,
        10,
        0,
        -1,
        14,
        0,
        0,
        11,
        0,
        0,
        13,
        0,
        0,
        14,
        0,
        0,
        15,
        0,
        6,
        12,
        1,
        1,
        12,
        2,
        1,
        5,
        3,
        1,
        11,
        5,
        1,
        8,
        34
      ],
      [
        0,
        0,
        0,
        0,
        0,
        0,
        0,
        0,
        0
      ],
      [
        -1,
        2,
        -1,
        2,
        -1,
        -1,
        2,
        7,
        -1
      ],
      [
        0,
        1,
        0,
        3,
        0,
        0,
        1,
        0,
        0
      ]
    ]
  ]
]